{
    "exercise-1": {
        "exerciseId" : "mp-351",
        "week" : "Semana 3",
        "day" : "Sexta",
        "name" : "Supino reto",
        "series" : 4,
        "reps-1" : 8,
        "reps-2" : 15,
        "pause" : 40,
        "c-speed" : 1, 
        "e-speed" : 3, 
        "technique-1" : "Pirâmide crescente",
        "description-1" : "null",
        "technique-2" : "null",
        "description-2" : "null",
        "technique-3" : "null",
        "description-3" : "null",
        "technique-4" : "null",
        "description-4" : "null",
        "is-grouping" : false,
        "weight" : 0
    },
    "exercise-2": {
        "exerciseId" : "mp-352",
        "week" : "Semana 3",
        "day" : "Sexta",
        "name" : "Supino inclinado",
        "series" : 3,
        "reps-1" : 3,
        "reps-2" : 7,
        "pause" : 40,
        "c-speed" : 1,
        "e-speed" : 1, 
        "technique-1" : "3 a 7",
        "description-1" : "null",
        "technique-2" : "null",
        "description-2" : "null",
        "technique-3" : "null",
        "description-3" : "null",
        "technique-4" : "null",
        "description-4" : "null",
        "is-grouping" : false,
        "weight" : 0
    },
    "exercise-3": {
        "exerciseId" : "mp-353",
        "week" : "Semana 3",
        "day" : "Sexta",
        "name" : "Crossover",
        "series" : 3,
        "reps-1" : 6,
        "reps-2" : 12,
        "pause" : 40,
        "c-speed" : 1, 
        "e-speed" : 3, 
        "technique-1" : "Pico",
        "description-1" : "null",
        "technique-2" : "null",
        "description-2" : "null",
        "technique-3" : "null",
        "description-3" : "null",
        "technique-4" : "null",
        "description-4" : "null",
        "is-grouping" : false,
        "weight" : 0
    },
    "exercise-4": {
        "exerciseId" : "mp-354",
        "week" : "Semana 3",
        "day" : "Sexta",
        "name" : "Desenvolvimento",
        "series" : 4,
        "reps-1" : 6,
        "reps-2" : 12,
        "pause" : 40,
        "c-speed" : 1,
        "e-speed" : 3, 
        "technique-1" : "Pirâmide crescente",
        "description-1" : "null",
        "technique-2" : "null",
        "description-2" : "null",
        "technique-3" : "null",
        "description-3" : "null",
        "technique-4" : "null",
        "description-4" : "null",
        "is-grouping" : false,
        "weight" : 0
    },
    "exercise-5": {
        "exerciseId" : "mp-355",
        "week" : "Semana 3",
        "day" : "Sexta",
        "name" : "Tríceps testa",
        "series" : 4,
        "reps-1" : 6,
        "reps-2" : 12,
        "pause" : 40,
        "c-speed" : 1, 
        "e-speed" : 3,
        "technique-1" : "Pirâmide crescente",
        "description-1" : "null",
        "technique-2" : "null",
        "description-2" : "null",
        "technique-3" : "null",
        "description-3" : "null",
        "technique-4" : "null",
        "description-4" : "null",
        "is-grouping" : false,
        "weight" : 0
    },
    "exercise-6": {
        "exerciseId" : "mp-356",
        "week" : "Semana 3",
        "day" : "Sexta",
        "name" : "Mergulho banco",
        "series" : 3,
        "reps-1" : 6,
        "reps-2" : 12,
        "pause" : 40,
        "c-speed" : 1, 
        "e-speed" : 1, 
        "technique-1" : "Falha concêntrica",
        "description-1" : "null",
        "technique-2" : "null",
        "description-2" : "null",
        "technique-3" : "null",
        "description-3" : "null",
        "technique-4" : "null",
        "description-4" : "null",
        "is-grouping" : false,
        "weight" : 0
    },
    "exercise-7": {
        "exerciseId" : "mp-357",
        "week" : "Semana 3",
        "day" : "Sexta",
        "name" : "Abs infra",
        "series" : 4,
        "reps-1" : 6,
        "reps-2" : 12,
        "pause" : 40,
        "c-speed" : 1, 
        "e-speed" : 3, 
        "technique-1" : "Falha concêntrica",
        "description-1" : "null",
        "technique-2" : "null",
        "description-2" : "null",
        "technique-3" : "null",
        "description-3" : "null",
        "technique-4" : "null",
        "description-4" : "null",
        "is-grouping" : false,
        "weight" : 0
    }
}