{
    "exercise-1": {
        "exerciseId" : 231,
        "week" : "Semana 2",
        "day" : "Quarta",
        "name" : "Agachamento livre",
        "series" : 4,
        "reps-1" : 8,
        "reps-2" : 15,
        "pause" : 40,
        "c-speed" : 1, 
        "e-speed" : 1, 
        "technique-1" : "Falha concêntrica",
        "technique-2" : "null",
        "technique-3" : "null",
        "technique-4" : "null",
        "description" : "null",
        "is-grouping" : false,
        "weight" : 0
    },
    "exercise-2": {
        "exerciseId" : 232,
        "week" : "Semana 2",
        "day" : "Quarta",
        "name" : "Leg press",
        "series" : 2,
        "reps-1" : 3,
        "reps-2" : 7,
        "pause" : 10,
        "c-speed" : 1, 
        "e-speed" : 1, 
        "technique-1" : "3 a 7",
        "technique-2" : "null",
        "technique-3" : "null",
        "technique-4" : "null",
        "description" : "null",
        "is-grouping" : false,
        "weight" : 0
    },
    "exercise-3": {
        "exerciseId" : 233,
        "week" : "Semana 2",
        "day" : "Quarta",
        "name" : "Agachamento frontal",
        "series" : 2,
        "reps-1" : 8,
        "reps-2" : 15,
        "pause" : 120,
        "c-speed" : 1, 
        "e-speed" : 1, 
        "technique-1" : "Falha concêntrica",
        "technique-2" : "null",
        "technique-3" : "null",
        "technique-4" : "null",
        "description" : "null",
        "is-grouping" : false,
        "weight" : 0
    },
    "exercise-4": {
        "exerciseId" : 234,
        "week" : "Semana 2",
        "day" : "Quarta",
        "name" : "Cadeira flexora",
        "series" : 3,
        "reps-1" : 8,
        "reps-2" : 15,
        "pause" : 40,
        "c-speed" : 1, 
        "e-speed" : 3, 
        "technique-1" : "Falha concêntrica",
        "technique-2" : "null",
        "technique-3" : "null",
        "technique-4" : "null",
        "description" : "null",
        "is-grouping" : false,
        "weight" : 0
    },
    "exercise-5": {
        "exerciseId" : 235,
        "week" : "Semana 2",
        "day" : "Quarta",
        "name" : "Panturrilha sentado",
        "series" : 4,
        "reps-1" : 8,
        "reps-2" : 15,
        "pause" : 30,
        "c-speed" : 1, 
        "e-speed" : 3, 
        "technique-1" : "Falha concêntrica",
        "technique-2" : "null",
        "technique-3" : "null",
        "technique-4" : "null",
        "description" : "null",
        "is-grouping" : false,
        "weight" : 0
    },
    "exercise-6": {
        "exerciseId" : 236,
        "week" : "Semana 2",
        "day" : "Quarta",
        "name" : "Panturrilha em pé",
        "series" : 3,
        "reps-1" : 8,
        "reps-2" : 15,
        "pause" : 30,
        "c-speed" : 1, 
        "e-speed" : 3, 
        "technique-1" : "Falha concêntrica",
        "technique-2" : "null",
        "technique-3" : "null",
        "technique-4" : "null",
        "description" : "null",
        "is-grouping" : false,
        "weight" : 0
    }
}